photoassistant/README.md
photoassistant/photoassistant-icon.ico
photoassistant/photoassistant-icon.ico.license
photoassistant/photoassistant-icon.png
photoassistant/photoassistant-icon.png.license
photoassistant/LICENSES/GPL-2.0-only.txt
photoassistant/core/filescan.py
photoassistant/core/metastorage.py
photoassistant/core/photo.py
photoassistant/core/photocollection.py
photoassistant/gui/qt/entry.py
photoassistant/gui/qt/imageviewer.py
photoassistant/gui/qt/photo.py
photoassistant/gui/qt/photodatamodel.py
photoassistant/gui/qt/photoview.py
photoassistant/gui/qt/photoviewitemdelegate.py
photoassistant/gui/qt/utils/qtutils.py
photoassistant/gui/resources/icon-broken-image.png
photoassistant/gui/resources/icon-broken-image.png.license
photoassistant/gui/resources/icon-loading.png
photoassistant/gui/resources/icon-loading.png.license
photoassistant/utils/cachingutils.py
photoassistant/utils/decoratorutils.py
photoassistant/utils/delayutils.py
photoassistant/utils/descriptors.py
photoassistant/utils/processingutils.py
photoassistant-1.1.2.dist-info/METADATA
photoassistant-1.1.2.dist-info/WHEEL
photoassistant-1.1.2.dist-info/entry_points.txt
photoassistant-1.1.2.dist-info/RECORD
