Metadata-Version: 2.1
Name: PhotoAssistant
Version: 1.1.2
Summary: PhotoAssistant: View and organize your photos for long-term storage. Simple, fast, effective.
Project-URL: Homepage, https://gitlab.com/AnthonyZimmermann/photoassistant
Project-URL: Sources, https://gitlab.com/AnthonyZimmermann/photoassistant
Author-email: Anthony Zimmermann <anthony.zimmermann@protonmail.com>
Keywords: image,images,imageviewer,organize,organizing,photo,photos,photoviewer,sort,sorting,view,viewer,viewing
Classifier: Development Status :: 3 - Alpha
Classifier: Intended Audience :: Developers
Classifier: Intended Audience :: End Users/Desktop
Classifier: License :: OSI Approved :: GNU General Public License v2 (GPLv2)
Classifier: Natural Language :: English
Classifier: Operating System :: MacOS :: MacOS X
Classifier: Operating System :: Microsoft
Classifier: Operating System :: Microsoft :: Windows
Classifier: Operating System :: POSIX
Classifier: Operating System :: POSIX :: Linux
Classifier: Programming Language :: Python
Classifier: Programming Language :: Python :: 3
Classifier: Programming Language :: Python :: 3 :: Only
Classifier: Programming Language :: Python :: 3.11
Classifier: Programming Language :: Python :: 3.12
Classifier: Programming Language :: Python :: 3.13
Classifier: Topic :: Multimedia
Classifier: Topic :: Multimedia :: Graphics :: Presentation
Classifier: Topic :: Multimedia :: Graphics :: Viewers
Classifier: Topic :: System :: Archiving
Classifier: Topic :: Utilities
Requires-Python: >=3.11
Requires-Dist: exifread<4.0.0,>=3.0.0
Requires-Dist: pyside6<7.0.0,>=6.6.1
